ts_featurizer/__init__.py
ts_featurizer/base/__init__.py
ts_featurizer/base/base.py
ts_featurizer/config/__init__.py
ts_featurizer/config/config_factory.py
ts_featurizer/config/default_config.py
ts_featurizer/tools/__init__.py
ts_featurizer/tools/base.py
ts_featurizer/tools/features.py
ts_featurizer/tools/featurizers.py
ts_featurizer/tools/helpers.py
ts_featurizer/tools/preprocessors.py
ts_featurizer/tools/transformers.py
tseries_featurizer-0.5.data/scripts/ts-featurizer
tseries_featurizer-0.5.dist-info/METADATA
tseries_featurizer-0.5.dist-info/WHEEL
tseries_featurizer-0.5.dist-info/top_level.txt
tseries_featurizer-0.5.dist-info/RECORD
