Metadata-Version: 2.1
Name: tseries-featurizer
Version: 0.5
Summary: A time series featurizer.
Home-page: https://bitbucket.org/joanesplazaola/time-series-featurizer
Author: Joanes Plazaola
Author-email: joanes.plazamadi@gmail.com
License: UNKNOWN
Platform: UNKNOWN
Classifier: Programming Language :: Python :: 3
Classifier: License :: OSI Approved :: MIT License
Classifier: Operating System :: OS Independent
Requires-Dist: pandas
Requires-Dist: scipy
Requires-Dist: statsmodels
Requires-Dist: pywt
Requires-Dist: matplotlib
